kuut/__init__.py
kuut/_modidx.py
kuut/core.py
kuut-0.0.3.dist-info/LICENSE
kuut-0.0.3.dist-info/METADATA
kuut-0.0.3.dist-info/WHEEL
kuut-0.0.3.dist-info/entry_points.txt
kuut-0.0.3.dist-info/top_level.txt
kuut-0.0.3.dist-info/RECORD
