Metadata-Version: 2.1
Name: kuut
Version: 0.0.3
Summary: taqadum: arabic for progress (tqdm). khutuat: arabic for steps (kuut)
Home-page: https://github.com/dsm-72/kuut
Author: dsm-72
Author-email: sumner.magruder@yale.edu
License: Apache Software License 2.0
Keywords: tqdm kuut progress step stepper interation iter substep notebook interactive
Classifier: Development Status :: 4 - Beta
Classifier: Intended Audience :: Developers
Classifier: Natural Language :: English
Classifier: Programming Language :: Python :: 3.7
Classifier: Programming Language :: Python :: 3.8
Classifier: Programming Language :: Python :: 3.9
Classifier: Programming Language :: Python :: 3.10
Classifier: License :: OSI Approved :: Apache Software License
Requires-Python: >=3.7
License-File: LICENSE
Requires-Dist: tqdm
Provides-Extra: dev
